euid-0.1.2.dist-info/METADATA
euid-0.1.2.dist-info/WHEEL
euid-0.1.2.dist-info/license_files/LICENSE
euid/__init__.py
euid/euid.abi3.so
euid-0.1.2.dist-info/RECORD
