Metadata-Version: 2.1
Name: euid
Version: 0.1.2
Classifier: Programming Language :: Python
Requires-Dist: euid
License-File: LICENSE
Summary: EUID for Python
Keywords: euid
Home-Page: https://github.com/ardikars/euid-python
Author: Ardika Rommy Sanjaya
Author-email: contact@ardikars.com
Maintainer-email: Ardika Rommy Sanjaya <contact@ardikars.com>
License: MIT
Requires-Python: >=3.7
Project-URL: homepage, https://github.com/ardikars/euid-python
Project-URL: documentation, https://readthedocs.org
Project-URL: repository, https://github.com/ardikars/euid-python
Project-URL: changelog, https://github.com/ardikars/euid-python/blob/master/CHANGELOG.md
